odoo10_addon_hr_attendance_rfid-10.0.1.0.1-nspkg.pth
odoo/addons/hr_attendance_rfid/README.rst
odoo/addons/hr_attendance_rfid/__init__.py
odoo/addons/hr_attendance_rfid/__manifest__.py
odoo/addons/hr_attendance_rfid/i18n/de.po
odoo/addons/hr_attendance_rfid/i18n/fr.po
odoo/addons/hr_attendance_rfid/i18n/hr_attendance_rfid.pot
odoo/addons/hr_attendance_rfid/models/__init__.py
odoo/addons/hr_attendance_rfid/models/hr_employee.py
odoo/addons/hr_attendance_rfid/security/hr_attendance_rfid.xml
odoo/addons/hr_attendance_rfid/security/ir.model.access.csv
odoo/addons/hr_attendance_rfid/static/description/icon.png
odoo/addons/hr_attendance_rfid/tests/__init__.py
odoo/addons/hr_attendance_rfid/tests/test_hr_attendance_rfid_process.py
odoo/addons/hr_attendance_rfid/views/hr_employee_view.xml
odoo10_addon_hr_attendance_rfid-10.0.1.0.1.dist-info/METADATA
odoo10_addon_hr_attendance_rfid-10.0.1.0.1.dist-info/WHEEL
odoo10_addon_hr_attendance_rfid-10.0.1.0.1.dist-info/namespace_packages.txt
odoo10_addon_hr_attendance_rfid-10.0.1.0.1.dist-info/top_level.txt
odoo10_addon_hr_attendance_rfid-10.0.1.0.1.dist-info/RECORD
